jcloudai_litellm/__init__.py
jcloudai_litellm/litellm.py
jcloudai_litellm-0.0.3.dist-info/METADATA
jcloudai_litellm-0.0.3.dist-info/WHEEL
jcloudai_litellm-0.0.3.dist-info/RECORD
